{
  "annotations": {"list": []},
  "editable": true,
  "description": "Event-driven grid: service health, HTTP golden signals (rate, errors, latency), Kafka event pipeline, and consumer lag. Use time range Last 15m and refresh 10s.",
  "fiscalYearStartMonth": 0,
  "graphTooltip": 1,
  "links": [],
  "liveNow": false,
  "panels": [
    {
      "collapsed": false,
      "gridPos": {"h": 1, "w": 24, "x": 0, "y": 0},
      "id": 100,
      "panels": [],
      "title": "Service status",
      "type": "row"
    },
    {
      "datasource": {"type": "prometheus", "uid": "prometheus"},
      "fieldConfig": {
        "defaults": {
          "color": {"mode": "thresholds"},
          "mappings": [
            {"options": {"0": {"color": "red", "index": 0, "text": "DOWN"}, "1": {"color": "green", "index": 1, "text": "UP"}}, "type": "value"},
            {"options": {"from": "", "to": "null", "result": {"color": "orange", "index": 0, "text": "NO DATA"}}, "type": "value"}
          ],
          "thresholds": {"mode": "absolute", "steps": [{"color": "red", "value": null}, {"color": "green", "value": 1}]},
          "unit": "short"
        },
        "overrides": []
      },
      "gridPos": {"h": 4, "w": 4, "x": 0, "y": 1},
      "id": 101,
      "options": {"colorMode": "value", "graphMode": "none", "justifyMode": "auto", "orientation": "auto", "reduceOptions": {"calcs": ["lastNotNull"], "fields": "", "values": false}, "textMode": "value_and_name"},
      "targets": [{"datasource": {"type": "prometheus", "uid": "prometheus"}, "expr": "up{job=\"event-ingest-service\"}", "legendFormat": "event-ingest", "refId": "A"}],
      "title": "event-ingest-service",
      "type": "stat"
    },
    {
      "datasource": {"type": "prometheus", "uid": "prometheus"},
      "fieldConfig": {
        "defaults": {
          "color": {"mode": "thresholds"},
          "mappings": [
            {"options": {"0": {"color": "red", "index": 0, "text": "DOWN"}, "1": {"color": "green", "index": 1, "text": "UP"}}, "type": "value"},
            {"options": {"from": "", "to": "null", "result": {"color": "orange", "index": 0, "text": "NO DATA"}}, "type": "value"}
          ],
          "thresholds": {"mode": "absolute", "steps": [{"color": "red", "value": null}, {"color": "green", "value": 1}]},
          "unit": "short"
        },
        "overrides": []
      },
      "gridPos": {"h": 4, "w": 4, "x": 4, "y": 1},
      "id": 102,
      "options": {"colorMode": "value", "graphMode": "none", "justifyMode": "auto", "orientation": "auto", "reduceOptions": {"calcs": ["lastNotNull"], "fields": "", "values": false}, "textMode": "value_and_name"},
      "targets": [{"datasource": {"type": "prometheus", "uid": "prometheus"}, "expr": "up{job=\"pricing-consumer-service\"}", "legendFormat": "pricing-consumer", "refId": "A"}],
      "title": "pricing-consumer-service",
      "type": "stat"
    },
    {
      "datasource": {"type": "prometheus", "uid": "prometheus"},
      "fieldConfig": {
        "defaults": {
          "color": {"mode": "thresholds"},
          "mappings": [
            {"options": {"0": {"color": "red", "index": 0, "text": "DOWN"}, "1": {"color": "green", "index": 1, "text": "UP"}}, "type": "value"},
            {"options": {"from": "", "to": "null", "result": {"color": "orange", "index": 0, "text": "NO DATA"}}, "type": "value"}
          ],
          "thresholds": {"mode": "absolute", "steps": [{"color": "red", "value": null}, {"color": "green", "value": 1}]},
          "unit": "short"
        },
        "overrides": []
      },
      "gridPos": {"h": 4, "w": 4, "x": 8, "y": 1},
      "id": 103,
      "options": {"colorMode": "value", "graphMode": "none", "justifyMode": "auto", "orientation": "auto", "reduceOptions": {"calcs": ["lastNotNull"], "fields": "", "values": false}, "textMode": "value_and_name"},
      "targets": [{"datasource": {"type": "prometheus", "uid": "prometheus"}, "expr": "up{job=\"alerting-service\"}", "legendFormat": "alerting", "refId": "A"}],
      "title": "alerting-service",
      "type": "stat"
    },
    {
      "datasource": {"type": "prometheus", "uid": "prometheus"},
      "fieldConfig": {
        "defaults": {
          "color": {"mode": "thresholds"},
          "mappings": [
            {"options": {"0": {"color": "red", "index": 0, "text": "DOWN"}, "1": {"color": "green", "index": 1, "text": "UP"}}, "type": "value"},
            {"options": {"from": "", "to": "null", "result": {"color": "orange", "index": 0, "text": "NO DATA"}}, "type": "value"}
          ],
          "thresholds": {"mode": "absolute", "steps": [{"color": "red", "value": null}, {"color": "green", "value": 1}]},
          "unit": "short"
        },
        "overrides": []
      },
      "gridPos": {"h": 4, "w": 4, "x": 12, "y": 1},
      "id": 104,
      "options": {"colorMode": "value", "graphMode": "none", "justifyMode": "auto", "orientation": "auto", "reduceOptions": {"calcs": ["lastNotNull"], "fields": "", "values": false}, "textMode": "value_and_name"},
      "targets": [{"datasource": {"type": "prometheus", "uid": "prometheus"}, "expr": "up{job=\"audit-service\"}", "legendFormat": "audit", "refId": "A"}],
      "title": "audit-service",
      "type": "stat"
    },
    {
      "datasource": {"type": "prometheus", "uid": "prometheus"},
      "fieldConfig": {
        "defaults": {
          "color": {"mode": "thresholds"},
          "mappings": [
            {"options": {"0": {"color": "red", "index": 0, "text": "DOWN"}, "1": {"color": "green", "index": 1, "text": "UP"}}, "type": "value"},
            {"options": {"from": "", "to": "null", "result": {"color": "orange", "index": 0, "text": "NO DATA"}}, "type": "value"}
          ],
          "thresholds": {"mode": "absolute", "steps": [{"color": "red", "value": null}, {"color": "green", "value": 1}]},
          "unit": "short"
        },
        "overrides": []
      },
      "gridPos": {"h": 4, "w": 4, "x": 16, "y": 1},
      "id": 105,
      "options": {"colorMode": "value", "graphMode": "none", "justifyMode": "auto", "orientation": "auto", "reduceOptions": {"calcs": ["lastNotNull"], "fields": "", "values": false}, "textMode": "value_and_name"},
      "targets": [{"datasource": {"type": "prometheus", "uid": "prometheus"}, "expr": "up{job=\"kafka-exporter\"}", "legendFormat": "kafka-exporter", "refId": "A"}],
      "title": "kafka-exporter",
      "type": "stat"
    },
    {
      "collapsed": false,
      "gridPos": {"h": 1, "w": 24, "x": 0, "y": 5},
      "id": 200,
      "panels": [],
      "title": "HTTP golden signals (by service)",
      "type": "row"
    },
    {
      "datasource": {"type": "prometheus", "uid": "prometheus"},
      "fieldConfig": {
        "defaults": {
          "color": {"mode": "palette-classic"},
          "custom": {"axisCenteredZero": false, "fillOpacity": 10},
          "unit": "reqps",
          "thresholds": {"mode": "absolute", "steps": [{"color": "green", "value": null}]}
        },
        "overrides": []
      },
      "gridPos": {"h": 8, "w": 12, "x": 0, "y": 6},
      "id": 201,
      "options": {"legend": {"displayMode": "list", "placement": "bottom", "showLegend": true}},
      "targets": [{"datasource": {"type": "prometheus", "uid": "prometheus"}, "expr": "sum(rate(http_server_requests_seconds_count{job=~\"event-ingest-service|pricing-consumer-service|alerting-service|audit-service\"}[5m])) by (job)", "legendFormat": "{{job}}", "refId": "A"}],
      "title": "Request rate (req/s, 5m)",
      "type": "timeseries"
    },
    {
      "datasource": {"type": "prometheus", "uid": "prometheus"},
      "fieldConfig": {
        "defaults": {
          "color": {"mode": "palette-classic"},
          "custom": {"axisCenteredZero": false, "fillOpacity": 10},
          "unit": "reqps",
          "thresholds": {"mode": "absolute", "steps": [{"color": "green", "value": null}, {"color": "red", "value": 0.01}]}
        },
        "overrides": []
      },
      "gridPos": {"h": 8, "w": 12, "x": 12, "y": 6},
      "id": 202,
      "options": {"legend": {"displayMode": "list", "placement": "bottom", "showLegend": true}},
      "targets": [{"datasource": {"type": "prometheus", "uid": "prometheus"}, "expr": "sum(rate(http_server_requests_seconds_count{job=~\"event-ingest-service|pricing-consumer-service|alerting-service|audit-service\",status=~\"5..\"}[5m])) by (job)", "legendFormat": "{{job}} 5xx", "refId": "A"}],
      "title": "Error rate 5xx (req/s, 5m)",
      "type": "timeseries"
    },
    {
      "datasource": {"type": "prometheus", "uid": "prometheus"},
      "fieldConfig": {
        "defaults": {
          "color": {"mode": "palette-classic"},
          "custom": {"axisCenteredZero": false, "fillOpacity": 10},
          "unit": "s",
          "thresholds": {"mode": "absolute", "steps": [{"color": "green", "value": null}, {"color": "yellow", "value": 0.5}, {"color": "red", "value": 1}]}
        },
        "overrides": []
      },
      "gridPos": {"h": 8, "w": 12, "x": 0, "y": 14},
      "id": 203,
      "options": {"legend": {"displayMode": "list", "placement": "bottom", "showLegend": true}},
      "targets": [{"datasource": {"type": "prometheus", "uid": "prometheus"}, "expr": "histogram_quantile(0.95, sum(rate(http_server_requests_seconds_bucket{job=~\"event-ingest-service|pricing-consumer-service|alerting-service|audit-service\"}[5m])) by (job, le))", "legendFormat": "{{job}} p95", "refId": "A"}],
      "title": "Latency p95 (seconds, 5m)",
      "type": "timeseries"
    },
    {
      "datasource": {"type": "prometheus", "uid": "prometheus"},
      "fieldConfig": {
        "defaults": {
          "color": {"mode": "palette-classic"},
          "custom": {"axisCenteredZero": false, "fillOpacity": 10},
          "unit": "short",
          "thresholds": {"mode": "absolute", "steps": [{"color": "green", "value": null}]}
        },
        "overrides": []
      },
      "gridPos": {"h": 8, "w": 12, "x": 12, "y": 14},
      "id": 204,
      "options": {"legend": {"displayMode": "list", "placement": "bottom", "showLegend": true}},
      "targets": [{"datasource": {"type": "prometheus", "uid": "prometheus"}, "expr": "sum(increase(http_server_requests_seconds_count{job=~\"event-ingest-service|pricing-consumer-service|alerting-service|audit-service\"}[1h])) by (job)", "legendFormat": "{{job}}", "refId": "A"}],
      "title": "Requests (last 1h total by service)",
      "type": "timeseries"
    },
    {
      "collapsed": false,
      "gridPos": {"h": 1, "w": 24, "x": 0, "y": 22},
      "id": 300,
      "panels": [],
      "title": "Event pipeline (Kafka)",
      "type": "row"
    },
    {
      "datasource": {"type": "prometheus", "uid": "prometheus"},
      "fieldConfig": {
        "defaults": {
          "color": {"mode": "palette-classic"},
          "custom": {"axisCenteredZero": false, "fillOpacity": 10},
          "unit": "short",
          "thresholds": {"mode": "absolute", "steps": [{"color": "green", "value": null}]}
        },
        "overrides": []
      },
      "gridPos": {"h": 8, "w": 12, "x": 0, "y": 23},
      "id": 301,
      "options": {"legend": {"displayMode": "list", "placement": "bottom", "showLegend": true}},
      "targets": [{"datasource": {"type": "prometheus", "uid": "prometheus"}, "expr": "sum(rate(kafka_topic_partition_current_offset{topic=\"grid.events.v1\"}[5m])) by (topic)", "legendFormat": "{{topic}}", "refId": "A"}],
      "title": "grid.events.v1 message rate (msg/s, 5m)",
      "type": "timeseries"
    },
    {
      "datasource": {"type": "prometheus", "uid": "prometheus"},
      "fieldConfig": {
        "defaults": {
          "color": {"mode": "palette-classic"},
          "custom": {"axisCenteredZero": false, "fillOpacity": 10},
          "unit": "short",
          "thresholds": {"mode": "absolute", "steps": [{"color": "green", "value": null}, {"color": "yellow", "value": 100}, {"color": "red", "value": 1000}]}
        },
        "overrides": []
      },
      "gridPos": {"h": 8, "w": 12, "x": 12, "y": 23},
      "id": 302,
      "options": {"legend": {"displayMode": "list", "placement": "bottom", "showLegend": true}},
      "targets": [{"datasource": {"type": "prometheus", "uid": "prometheus"}, "expr": "sum(kafka_consumergroup_lag) by (consumergroup, topic)", "legendFormat": "{{consumergroup}} ({{topic}})", "refId": "A"}],
      "title": "Consumer group lag (events behind)",
      "type": "timeseries"
    },
    {
      "datasource": {"type": "prometheus", "uid": "prometheus"},
      "fieldConfig": {
        "defaults": {
          "color": {"mode": "palette-classic"},
          "custom": {"align": "auto", "displayMode": "auto"},
          "mappings": [],
          "thresholds": {"mode": "absolute", "steps": [{"color": "green", "value": null}]}
        },
        "overrides": []
      },
      "gridPos": {"h": 6, "w": 24, "x": 0, "y": 31},
      "id": 303,
      "options": {"cellHeight": "sm", "footer": {"show": false}, "showHeader": true, "sortBy": [{"desc": true, "displayName": "Lag"}]},
      "targets": [{"datasource": {"type": "prometheus", "uid": "prometheus"}, "expr": "sum(kafka_consumergroup_lag) by (consumergroup, topic)", "format": "table", "instant": true, "refId": "A"}],
      "title": "Consumer groups lag (current)",
      "transformations": [{"id": "merge", "options": {}}, {"id": "organize", "options": {"excludeByName": {"Time": true}, "renameByName": {"consumergroup": "Consumer group", "topic": "Topic", "Value": "Lag"}}}],
      "type": "table"
    },
    {
      "collapsed": false,
      "gridPos": {"h": 1, "w": 24, "x": 0, "y": 37},
      "id": 400,
      "panels": [],
      "title": "JVM (per service)",
      "type": "row"
    },
    {
      "datasource": {"type": "prometheus", "uid": "prometheus"},
      "fieldConfig": {
        "defaults": {
          "color": {"mode": "palette-classic"},
          "custom": {"axisCenteredZero": false, "fillOpacity": 10},
          "unit": "bytes",
          "thresholds": {"mode": "absolute", "steps": [{"color": "green", "value": null}]}
        },
        "overrides": []
      },
      "gridPos": {"h": 6, "w": 12, "x": 0, "y": 38},
      "id": 401,
      "options": {"legend": {"displayMode": "list", "placement": "bottom", "showLegend": true}},
      "targets": [{"datasource": {"type": "prometheus", "uid": "prometheus"}, "expr": "sum(jvm_memory_used_bytes{job=~\"event-ingest-service|pricing-consumer-service|alerting-service|audit-service\"}) by (job, area)", "legendFormat": "{{job}} {{area}}", "refId": "A"}],
      "title": "JVM memory used by service",
      "type": "timeseries"
    },
    {
      "datasource": {"type": "prometheus", "uid": "prometheus"},
      "fieldConfig": {
        "defaults": {
          "color": {"mode": "palette-classic"},
          "custom": {"axisCenteredZero": false, "fillOpacity": 10},
          "unit": "short",
          "thresholds": {"mode": "absolute", "steps": [{"color": "green", "value": null}]}
        },
        "overrides": []
      },
      "gridPos": {"h": 6, "w": 12, "x": 12, "y": 38},
      "id": 402,
      "options": {"legend": {"displayMode": "list", "placement": "bottom", "showLegend": true}},
      "targets": [{"datasource": {"type": "prometheus", "uid": "prometheus"}, "expr": "jvm_threads_live_threads{job=~\"event-ingest-service|pricing-consumer-service|alerting-service|audit-service\"}", "legendFormat": "{{job}}", "refId": "A"}],
      "title": "JVM live threads",
      "type": "timeseries"
    }
  ],
  "refresh": "10s",
  "schemaVersion": 38,
  "tags": ["event-grid", "observability"],
  "templating": {
    "list": [
      {
        "current": {"selected": true, "text": "All", "value": "$__all"},
        "datasource": {"type": "prometheus", "uid": "prometheus"},
        "definition": "label_values(up{job=~\"event-ingest-service|pricing-consumer-service|alerting-service|audit-service\"}, job)",
        "hide": 0,
        "includeAll": true,
        "label": "Service",
        "multi": true,
        "name": "service",
        "options": [],
        "query": "label_values(up{job=~\"event-ingest-service|pricing-consumer-service|alerting-service|audit-service\"}, job)",
        "refresh": 1,
        "regex": "",
        "skipUrlSync": false,
        "sort": 1,
        "type": "query"
      }
    ]
  },
  "time": {"from": "now-15m", "to": "now"},
  "timepicker": {},
  "timezone": "browser",
  "title": "Event Grid - Overview",
  "uid": "event-grid-overview",
  "version": 1
}
